easy_gmssl/__init__.py
easy_gmssl/easy_random_data.py
easy_gmssl/easy_random_data_test.py
easy_gmssl/easy_sm2_key.py
easy_gmssl/easy_sm2_key_test.py
easy_gmssl/easy_sm2_sign_key.py
easy_gmssl/easy_sm2_sign_test.py
easy_gmssl/easy_sm3_key.py
easy_gmssl/easy_sm3_key_test.py
easy_gmssl/easy_sm4_key.py
easy_gmssl/easy_sm4_test.py
easy_gmssl/easy_zuc.py
easy_gmssl/easy_zuc_test.py
easy_gmssl/gmssl.py
easy_gmssl-1.2.3.dist-info/METADATA
easy_gmssl-1.2.3.dist-info/WHEEL
easy_gmssl-1.2.3.dist-info/top_level.txt
easy_gmssl-1.2.3.dist-info/RECORD
