Metadata-Version: 2.1
Name: easy_gmssl
Version: 1.2.3
Summary: easy gmssl for python
Home-page: https://cloud.tencent.com/developer/user/1371154/articles
Author: bowenerchen
Author-email: bowenerchen@foxmail.com
Classifier: License :: OSI Approved :: MIT License
Classifier: Programming Language :: Python :: 3
Classifier: License :: OSI Approved :: Apache Software License
Requires-Python: >=3.8
